openassetio_mediacreation/__init__.py
openassetio_mediacreation/traits.yml
openassetio_mediacreation/specifications/__init__.py
openassetio_mediacreation/specifications/application.py
openassetio_mediacreation/specifications/audio.py
openassetio_mediacreation/specifications/lifecycle.py
openassetio_mediacreation/specifications/representation.py
openassetio_mediacreation/specifications/threeDimensional.py
openassetio_mediacreation/specifications/twoDimensional.py
openassetio_mediacreation/traits/__init__.py
openassetio_mediacreation/traits/application.py
openassetio_mediacreation/traits/audio.py
openassetio_mediacreation/traits/auth.py
openassetio_mediacreation/traits/color.py
openassetio_mediacreation/traits/content.py
openassetio_mediacreation/traits/identity.py
openassetio_mediacreation/traits/imaging.py
openassetio_mediacreation/traits/lifecycle.py
openassetio_mediacreation/traits/managementPolicy.py
openassetio_mediacreation/traits/metadata.py
openassetio_mediacreation/traits/relationship.py
openassetio_mediacreation/traits/representation.py
openassetio_mediacreation/traits/threeDimensional.py
openassetio_mediacreation/traits/timeDomain.py
openassetio_mediacreation/traits/twoDimensional.py
openassetio_mediacreation/traits/ui.py
openassetio_mediacreation/traits/uiPolicy.py
openassetio_mediacreation/traits/usage.py
openassetio_mediacreation-1.0.0a13.dist-info/licenses/LICENSE
openassetio_mediacreation-1.0.0a13.dist-info/METADATA
openassetio_mediacreation-1.0.0a13.dist-info/WHEEL
openassetio_mediacreation-1.0.0a13.dist-info/top_level.txt
openassetio_mediacreation-1.0.0a13.dist-info/RECORD
