Metadata-Version: 2.4
Name: openassetio-mediacreation
Version: 1.0.0a13
Author-email: Contributors to the OpenAssetIO project <openassetio-discussion@lists.aswf.io>
Project-URL: OpenAssetIO, https://github.com/OpenAssetIO/OpenAssetIO
Project-URL: Source, https://github.com/OpenAssetIO/OpenAssetIO-MediaCreation
Project-URL: Issues, https://github.com/OpenAssetIO/OpenAssetIO-MediaCreation/issues
Keywords: openassetio,mediacreation,trait
Classifier: Development Status :: 3 - Alpha
Classifier: Intended Audience :: Developers
Classifier: License :: OSI Approved :: Apache Software License
Classifier: Natural Language :: English
Classifier: Operating System :: MacOS
Classifier: Operating System :: Microsoft :: Windows
Classifier: Operating System :: POSIX :: Linux
Classifier: Programming Language :: Python :: 3
Classifier: Topic :: Software Development :: Libraries :: Python Modules
Requires-Python: >=3.10
License-File: LICENSE
Requires-Dist: openassetio>=1.0.0b2
Dynamic: license-file
